CHANGES.md
MANIFEST.in
README.md
setup.py
croncoat/__init__.py
croncoat.egg-info/PKG-INFO
croncoat.egg-info/SOURCES.txt
croncoat.egg-info/dependency_links.txt
croncoat.egg-info/entry_points.txt
croncoat.egg-info/requires.txt
croncoat.egg-info/top_level.txt
croncoat/cc/__init__.py
croncoat/cc/cronwrapper.py
croncoat/cc/expiringcommand.py
croncoat/cc/helper.py
croncoat/cc/mailbackend.py
croncoat/scripts/__init__.py
croncoat/scripts/ccscript.py
croncoat/test/__init__.py
croncoat/test/test_cw.py