Metadata-Version: 1.1
Name: croncoat
Version: 0.4
Summary: croncoat extends cronwrap, a cron job wrapper that wraps jobs and enables better error reporting and command timeouts.
Home-page: https://github.com/MatthiasKauer/croncoat
Author: Matthias Kauer
Author-email: mk.software@zuez.org
License: BSD
Keywords: cron wrapper crontab cronjob email
Platform: Unix
Classifier: Development Status :: 4 - Beta
Classifier: Environment :: Console
Classifier: Intended Audience :: System Administrators
Classifier: License :: OSI Approved :: BSD License
Classifier: Operating System :: Unix
Classifier: Programming Language :: Python
